pacersdk/__init__.py
pacersdk/auth.py
pacersdk/client.py
pacersdk/config.py
pacersdk/default.json
pacersdk/otp.py
pacersdk/session.py
pacersdk/models/__init__.py
pacersdk/models/billing.py
pacersdk/models/cases.py
pacersdk/models/courts.py
pacersdk/models/parties.py
pacersdk/models/query.py
pacersdk/models/reports.py
pacersdk/models/sort.py
pacersdk/models/types.py
pacersdk/services/__init__.py
pacersdk/services/batch_case.py
pacersdk/services/batch_party.py
pacersdk/services/case.py
pacersdk/services/party.py
pacersdk-0.1.1.dist-info/licenses/LICENSE
pacersdk-0.1.1.dist-info/METADATA
pacersdk-0.1.1.dist-info/WHEEL
pacersdk-0.1.1.dist-info/top_level.txt
pacersdk-0.1.1.dist-info/RECORD
