Metadata-Version: 2.4
Name: pacersdk
Version: 0.1.1
Summary: Python SDK for accessing the PACER API
License: BSD 3-Clause License
Project-URL: homepage, https://github.com/mcpcpc/pacersdk
Project-URL: repository, https://github.com/mcpcpc/pacersdk
Project-URL: changelog, https://github.com/mcpcpc/pacersdk/blob/main/CHANGELOG.md
Keywords: pacer,client
Requires-Python: >=3.11
License-File: LICENSE
Provides-Extra: dev
Requires-Dist: black; extra == "dev"
Provides-Extra: docs
Requires-Dist: sphinx; extra == "docs"
Requires-Dist: furo; extra == "docs"
Dynamic: license-file
